acedb/__init__.py
acedb/acedb.py
acedb/cli.py
acedb/config.py
acedb/dbnclient.py
acedb/fredclient.py
acedb/postgreclient.py
acedb-0.1.6.dist-info/licenses/LICENSE.md
acedb-0.1.6.dist-info/METADATA
acedb-0.1.6.dist-info/WHEEL
acedb-0.1.6.dist-info/entry_points.txt
acedb-0.1.6.dist-info/top_level.txt
acedb-0.1.6.dist-info/RECORD
