Metadata-Version: 2.4
Name: acedb
Version: 0.1.6
Summary: Wrapper for ACE ETH Postgres database
Author-email: Carlo Teufel <carlo.teufel@analytics-club.org>
License: MIT
Classifier: Programming Language :: Python :: 3
Classifier: License :: OSI Approved :: MIT License
Classifier: Operating System :: OS Independent
License-File: LICENSE.md
Requires-Dist: polars==1.27.1
Requires-Dist: psycopg2-binary==2.9.10
Requires-Dist: databento==0.52.0
Requires-Dist: click==8.1.8
Requires-Dist: build==1.2.2.post1
Requires-Dist: setuptools==65.5.0
Requires-Dist: fredapi==0.5.2
Dynamic: license-file
